Workbook

Sheet Profile
A1: SOCIAL PROFILE (V.2017-0) | D1: Value chain: | F1: Maize
D2: Country : | E2: Georgia
A3: Date last modif. | B3: . . / . . / 20 . .
A12: Domain | C12: Present profile | E12: Trend | F12: Previous profile | G12: =Register!H3 -> ../../20..
C13: Score level | D13: Count | F13: Score level | G13: Count | I13: Tr_score
A14: =Register!A5 -> 1. WORKING CONDITIONS | C14: =Register!C10 -> Substantial | D14: =Register!B10 -> 2.725 | E14: =Register!D10 -> ↑ | F14: =Register!I10 -> Not at all | G14: =Register!H10 -> 0 | I14: =Register!#REF! -> #REF!
A15: =Register!A11 -> 2. LAND & WATER RIGHTS | C15: =Register!C15 -> Substantial | D15: =Register!B15 -> 2.6111111 | E15: =Register!D15 -> ↑ | F15: =Register!I15 -> Not at all | G15: =Register!H15 -> 0 | I15: =Register!#REF! -> #REF!
A16: =Register!A16 -> 3. GENDER EQUALITY | C16: =Register!C22 -> Substantial | D16: =Register!B22 -> 2.86 | E16: =Register!D22 -> ↑ | F16: =Register!I22 -> Not at all | G16: =Register!H22 -> 0 | I16: =Register!#REF! -> #REF!
A17: =Register!A23 -> 4. FOOD AND NUTRITION SECURITY | C17: =Register!C28 -> Substantial | D17: =Register!B28 -> 2.75 | E17: =Register!D28 -> ↑ | F17: =Register!I28 -> Not at all | G17: =Register!H28 -> 0 | I17: =Register!#REF! -> #REF!
A18: =Register!A29 -> 5. SOCIAL CAPITAL | C18: =Register!C33 -> Substantial | D18: =Register!B33 -> 2.9444444 | E18: =Register!D33 -> ↑ | F18: =Register!I33 -> Not at all | G18: =Register!H33 -> 0
A19: =Register!A34 -> 6. LIVING CONDITIONS | C19: =Register!C39 -> Substantial | D19: =Register!B39 -> 2.7222222 | E19: =Register!D39 -> ↑ | F19: =Register!I39 -> Not at all | G19: =Register!H39 -> 0 | I19: =Register!#REF! -> #REF!
I20: =AVERAGE(I14:I19) -> #REF!
A21: Overall Recommendation
A24: Major Issues
A26: Risk/Cost of Non-Intervention vs. Benefits
A28: Key Mitigating Measures

Sheet Sheet1
G9: Domain | I9: Present profile
I10: Score level | J10: Count
G11: 1. WORKING CONDITIONS | I11: Substantial | J11: 2.925
G12: 2. LAND & WATER RIGHTS | I12: Substantial | J12: 2.7222222
G13: 3. GENDER EQUALITY | I13: Substantial | J13: 2.78
G14: 4. FOOD AND NUTRITION SECURITY | I14: Substantial | J14: 3.4583333
G15: 5. SOCIAL CAPITAL | I15: Substantial | J15: 3.1388889
G16: 6. LIVING CONDITIONS | I16: Substantial | J16: 3.3333333

Sheet Register
A1: =Profile!F1 -> Maize | C1: Country: | D1: =Profile!E2 -> Georgia | F1: Date Last Modification: | G1: =Profile!B3 -> . . / . . / 20 . . | H1: Previous Analysis
A2: Dimension | B2: Count | C2: Score level | D2: Trend | E2: Major risks and possible negative consequences | F2: Mitigating measures | G2: Comments | H2: date:
H3: ../../20.. | L3: =Questionnaire!$N$3 -> High | M3: Zero
H4: Score | I4: Level | L4: =Questionnaire!$N$4 -> Substantial | M4: Low
A5: =Questionnaire!$A$3 -> 1. WORKING CONDITIONS | L5: =Questionnaire!$N$5 -> Moderate/Low | M5: Medium
A6: =Questionnaire!$A$4 -> 1.1 Respect of labour rights | B6: =Questionnaire!J10 -> 2.4 | C6: =IF(B6<1.5,$L$6,IF(B6<2.5,$L$5,IF(B6<3.5,$L$4,IF(B6<4.5,$L$3,"n/a")))) -> Moderate/Low | D6: =IF(H6<B6,"↑",IF(H6>B6,"↓","↔")) -> ↑ | H6: 0 | I6: =IF(H6<1.5,$L$6,IF(H6<2.5,$L$5,IF(H6<3.5,$L$4,IF(H6<4.5,$L$3,"n/a")))) -> Not at all | K6: ↑ | L6: =Questionnaire!$N$6 -> Not at all | M6: High
A7: =Questionnaire!$A$11 -> 1.2 Child Labour | B7: =Questionnaire!J14 -> 4 | C7: =IF(B7<1.5,$L$6,IF(B7<2.5,$L$5,IF(B7<3.5,$L$4,IF(B7<4.5,$L$3,"n/a")))) -> High | D7: =IF(H7<B7,"↑",IF(H7>B7,"↓","↔")) -> ↑ | H7: 0 | I7: =IF(H7<1.5,$L$6,IF(H7<2.5,$L$5,IF(H7<3.5,$L$4,IF(H7<4.5,$L$3,"n/a")))) -> Not at all | K7: ↓ | L7: =Questionnaire!$N$7 -> n/a
A8: =Questionnaire!$A$15 -> 1.3 Job safety | B8: =Questionnaire!J17 -> 2 | C8: =IF(B8<1.5,$L$6,IF(B8<2.5,$L$5,IF(B8<3.5,$L$4,IF(B8<4.5,$L$3,"n/a")))) -> Moderate/Low | D8: =IF(H8<B8,"↑",IF(H8>B8,"↓","↔")) -> ↑ | H8: 0 | I8: =IF(H8<1.5,$L$6,IF(H8<2.5,$L$5,IF(H8<3.5,$L$4,IF(H8<4.5,$L$3,"n/a")))) -> Not at all | K8: ↔
A9: =Questionnaire!$A$18 -> 1.4 Attractiveness | B9: =Questionnaire!J21 -> 2.5 | C9: =IF(B9<1.5,$L$6,IF(B9<2.5,$L$5,IF(B9<3.5,$L$4,IF(B9<4.5,$L$3,"n/a")))) -> Substantial | D9: =IF(H9<B9,"↑",IF(H9>B9,"↓","↔")) -> ↑ | H9: 0 | I9: =IF(H9<1.5,$L$6,IF(H9<2.5,$L$5,IF(H9<3.5,$L$4,IF(H9<4.5,$L$3,"n/a")))) -> Not at all
A10: Average | B10: =IF(COUNT(B6:B9)=0,"n/a",(AVERAGE(B6:B9))) -> 2.725 | C10: =IF(B10<1.5,$L$6,IF(B10<2.5,$L$5,IF(B10<3.5,$L$4,IF(B10<4.5,$L$3,"n/a")))) -> Substantial | D10: =IF(H10<B10,"↑",IF(H10>B10,"↓","↔")) -> ↑ | H10: =AVERAGE(H6:H9) -> 0 | I10: =IF(H10<1.5,$L$6,IF(H10<2.5,$L$5,IF(H10<3.5,$L$4,IF(H10<4.5,$L$3,"n/a")))) -> Not at all
A11: =Questionnaire!$A$22 -> 2. LAND & WATER RIGHTS
A12: =Questionnaire!$A$23 -> 2.1 Adherence to VGGT | B12: =Questionnaire!J26 -> 2.5 | C12: =IF(B12<1.5,$L$6,IF(B12<2.5,$L$5,IF(B12<3.5,$L$4,IF(B12<4.5,$L$3,"n/a")))) -> Substantial | D12: =IF(H12<B12,"↑",IF(H12>B12,"↓","↔")) -> ↑ | H12: 0 | I12: =IF(H12<1.5,$L$6,IF(H12<2.5,$L$5,IF(H12<3.5,$L$4,IF(H12<4.5,$L$3,"n/a")))) -> Not at all
A13: =Questionnaire!$A$27 -> 2.2 Transparency, participation and consultation | B13: =Questionnaire!J32 -> 2.3333333 | C13: =IF(B13<1.5,$L$6,IF(B13<2.5,$L$5,IF(B13<3.5,$L$4,IF(B13<4.5,$L$3,"n/a")))) -> Moderate/Low | D13: =IF(H13<B13,"↑",IF(H13>B13,"↓","↔")) -> ↑ | H13: 0 | I13: =IF(H13<1.5,$L$6,IF(H13<2.5,$L$5,IF(H13<3.5,$L$4,IF(H13<4.5,$L$3,"n/a")))) -> Not at all
A14: =Questionnaire!$A$33 -> 2.3 Equity,compensation and justice | B14: =Questionnaire!J38 -> 3 | C14: =IF(B14<1.5,$L$6,IF(B14<2.5,$L$5,IF(B14<3.5,$L$4,IF(B14<4.5,$L$3,"n/a")))) -> Substantial | D14: =IF(H14<B14,"↑",IF(H14>B14,"↓","↔")) -> ↑ | H14: 0 | I14: =IF(H14<1.5,$L$6,IF(H14<2.5,$L$5,IF(H14<3.5,$L$4,IF(H14<4.5,$L$3,"n/a")))) -> Not at all
A15: Average | B15: =IF(COUNT(B12:B14)=0,"n/a",(AVERAGE(B12:B14))) -> 2.6111111 | C15: =IF(B15<1.5,$L$6,IF(B15<2.5,$L$5,IF(B15<3.5,$L$4,IF(B15<4.5,$L$3,"n/a")))) -> Substantial | D15: =IF(H15<B15,"↑",IF(H15>B15,"↓","↔")) -> ↑ | H15: =AVERAGE(H12:H14) -> 0 | I15: =IF(H15<1.5,$L$6,IF(H15<2.5,$L$5,IF(H15<3.5,$L$4,IF(H15<4.5,$L$3,"n/a")))) -> Not at all
A16: =Questionnaire!$A$39 -> 3. GENDER EQUALITY
A17: =Questionnaire!$A$40 -> 3.1 Economic activities | B17: =Questionnaire!J43 -> 3 | C17: =IF(B17<1.5,$L$6,IF(B17<2.5,$L$5,IF(B17<3.5,$L$4,IF(B17<4.5,$L$3,"n/a")))) -> Substantial | D17: =IF(H17<B17,"↑",IF(H17>B17,"↓","↔")) -> ↑ | H17: 0 | I17: =IF(H17<1.5,$L$6,IF(H17<2.5,$L$5,IF(H17<3.5,$L$4,IF(H17<4.5,$L$3,"n/a")))) -> Not at all
A18: =Questionnaire!$A$44 -> 3.2 Access to resources and services | B18: =Questionnaire!J49 -> 2.5 | C18: =IF(B18<1.5,$L$6,IF(B18<2.5,$L$5,IF(B18<3.5,$L$4,IF(B18<4.5,$L$3,"n/a")))) -> Substantial | D18: =IF(H18<B18,"↑",IF(H18>B18,"↓","↔")) -> ↑ | H18: 0 | I18: =IF(H18<1.5,$L$6,IF(H18<2.5,$L$5,IF(H18<3.5,$L$4,IF(H18<4.5,$L$3,"n/a")))) -> Not at all
A19: =Questionnaire!$A$50 -> 3.3 Decision making | B19: =Questionnaire!J56 -> 2.8 | C19: =IF(B19<1.5,$L$6,IF(B19<2.5,$L$5,IF(B19<3.5,$L$4,IF(B19<4.5,$L$3,"n/a")))) -> Substantial | D19: =IF(H19<B19,"↑",IF(H19>B19,"↓","↔")) -> ↑ | H19: 0 | I19: =IF(H19<1.5,$L$6,IF(H19<2.5,$L$5,IF(H19<3.5,$L$4,IF(H19<4.5,$L$3,"n/a")))) -> Not at all
A20: =Questionnaire!$A$57 -> 3.4 Leadership and empowerment | B20: =Questionnaire!J62 -> 3 | C20: =IF(B20<1.5,$L$6,IF(B20<2.5,$L$5,IF(B20<3.5,$L$4,IF(B20<4.5,$L$3,"n/a")))) -> Substantial | D20: =IF(H20<B20,"↑",IF(H20>B20,"↓","↔")) -> ↑ | H20: 0 | I20: =IF(H20<1.5,$L$6,IF(H20<2.5,$L$5,IF(H20<3.5,$L$4,IF(H20<4.5,$L$3,"n/a")))) -> Not at all
A21: =Questionnaire!$A$63 -> 3.5 Hardship and division of labour | B21: =Questionnaire!J66 -> 3 | C21: =IF(B21<1.5,$L$6,IF(B21<2.5,$L$5,IF(B21<3.5,$L$4,IF(B21<4.5,$L$3,"n/a")))) -> Substantial | D21: =IF(H21<B21,"↑",IF(H21>B21,"↓","↔")) -> ↑ | H21: 0 | I21: =IF(H21<1.5,$L$6,IF(H21<2.5,$L$5,IF(H21<3.5,$L$4,IF(H21<4.5,$L$3,"n/a")))) -> Not at all
A22: Average | B22: =IF(COUNT(B17:B21)=0,"n/a",(AVERAGE(B17:B21))) -> 2.86 | C22: =IF(B22<1.5,$L$6,IF(B22<2.5,$L$5,IF(B22<3.5,$L$4,IF(B22<4.5,$L$3,"n/a")))) -> Substantial | D22: =IF(H22<B22,"↑",IF(H22>B22,"↓","↔")) -> ↑ | H22: =AVERAGE(H17:H21) -> 0 | I22: =IF(H22<1.5,$L$6,IF(H22<2.5,$L$5,IF(H22<3.5,$L$4,IF(H22<4.5,$L$3,"n/a")))) -> Not at all
A23: =Questionnaire!$A$67 -> 4. FOOD AND NUTRITION SECURITY
A24: =Questionnaire!$A$68 -> 4.1 Availability of food | B24: =Questionnaire!J71 -> 3 | C24: =IF(B24<1.5,$L$6,IF(B24<2.5,$L$5,IF(B24<3.5,$L$4,IF(B24<4.5,$L$3,"n/a")))) -> Substantial | D24: =IF(H24<B24,"↑",IF(H24>B24,"↓","↔")) -> ↑ | H24: 0 | I24: =IF(H24<1.5,$L$6,IF(H24<2.5,$L$5,IF(H24<3.5,$L$4,IF(H24<4.5,$L$3,"n/a")))) -> Not at all
A25: =Questionnaire!$A$72 -> 4.2 Accessibility of food | B25: =Questionnaire!J75 -> 2.5 | C25: =IF(B25<1.5,$L$6,IF(B25<2.5,$L$5,IF(B25<3.5,$L$4,IF(B25<4.5,$L$3,"n/a")))) -> Substantial | D25: =IF(H25<B25,"↑",IF(H25>B25,"↓","↔")) -> ↑ | H25: 0 | I25: =IF(H25<1.5,$L$6,IF(H25<2.5,$L$5,IF(H25<3.5,$L$4,IF(H25<4.5,$L$3,"n/a")))) -> Not at all
A26: =Questionnaire!$A$76 -> 4.3 Utilisation and nutritional adequacy | B26: =Questionnaire!J80 -> 3 | C26: =IF(B26<1.5,$L$6,IF(B26<2.5,$L$5,IF(B26<3.5,$L$4,IF(B26<4.5,$L$3,"n/a")))) -> Substantial | D26: =IF(H26<B26,"↑",IF(H26>B26,"↓","↔")) -> ↑ | H26: 0 | I26: =IF(H26<1.5,$L$6,IF(H26<2.5,$L$5,IF(H26<3.5,$L$4,IF(H26<4.5,$L$3,"n/a")))) -> Not at all
A27: =Questionnaire!$A$81 -> 4.4 Stability | B27: =Questionnaire!J84 -> 2.5 | C27: =IF(B27<1.5,$L$6,IF(B27<2.5,$L$5,IF(B27<3.5,$L$4,IF(B27<4.5,$L$3,"n/a")))) -> Substantial | D27: =IF(H27<B27,"↑",IF(H27>B27,"↓","↔")) -> ↑ | H27: 0 | I27: =IF(H27<1.5,$L$6,IF(H27<2.5,$L$5,IF(H27<3.5,$L$4,IF(H27<4.5,$L$3,"n/a")))) -> Not at all
A28: Average | B28: =IF(COUNT(B24:B27)=0,"n/a",(AVERAGE(B24:B27))) -> 2.75 | C28: =IF(B28<1.5,$L$6,IF(B28<2.5,$L$5,IF(B28<3.5,$L$4,IF(B28<4.5,$L$3,"n/a")))) -> Substantial | D28: =IF(H28<B28,"↑",IF(H28>B28,"↓","↔")) -> ↑ | H28: =AVERAGE(H24:H27) -> 0 | I28: =IF(H28<1.5,$L$6,IF(H28<2.5,$L$5,IF(H28<3.5,$L$4,IF(H28<4.5,$L$3,"n/a")))) -> Not at all
A29: =Questionnaire!$A$85 -> 5. SOCIAL CAPITAL
A30: =Questionnaire!$A$86 -> 5.1 Strength of producer organisations | B30: =Questionnaire!J91 -> 2.5 | C30: =IF(B30<1.5,$L$6,IF(B30<2.5,$L$5,IF(B30<3.5,$L$4,IF(B30<4.5,$L$3,"n/a")))) -> Substantial | D30: =IF(H30<B30,"↑",IF(H30>B30,"↓","↔")) -> ↑ | H30: 0 | I30: =IF(H30<1.5,$L$6,IF(H30<2.5,$L$5,IF(H30<3.5,$L$4,IF(H30<4.5,$L$3,"n/a")))) -> Not at all
A31: =Questionnaire!$A$92 -> 5.2 Information and confidence | B31: =Questionnaire!J95 -> 3 | C31: =IF(B31<1.5,$L$6,IF(B31<2.5,$L$5,IF(B31<3.5,$L$4,IF(B31<4.5,$L$3,"n/a")))) -> Substantial | D31: =IF(H31<B31,"↑",IF(H31>B31,"↓","↔")) -> ↑ | H31: 0 | I31: =IF(H31<1.5,$L$6,IF(H31<2.5,$L$5,IF(H31<3.5,$L$4,IF(H31<4.5,$L$3,"n/a")))) -> Not at all
A32: =Questionnaire!$A$96 -> 5.3 Social involvement | B32: =Questionnaire!J100 -> 3.3333333 | C32: =IF(B32<1.5,$L$6,IF(B32<2.5,$L$5,IF(B32<3.5,$L$4,IF(B32<4.5,$L$3,"n/a")))) -> Substantial | D32: =IF(H32<B32,"↑",IF(H32>B32,"↓","↔")) -> ↑ | H32: 0 | I32: =IF(H32<1.5,$L$6,IF(H32<2.5,$L$5,IF(H32<3.5,$L$4,IF(H32<4.5,$L$3,"n/a")))) -> Not at all
A33: Average | B33: =IF(COUNT(B30:B32)=0,"n/a",(AVERAGE(B30:B32))) -> 2.9444444 | C33: =IF(B33<1.5,$L$6,IF(B33<2.5,$L$5,IF(B33<3.5,$L$4,IF(B33<4.5,$L$3,"n/a")))) -> Substantial | D33: =IF(H33<B33,"↑",IF(H33>B33,"↓","↔")) -> ↑ | H33: =AVERAGE(H30:H32) -> 0 | I33: =IF(H33<1.5,$L$6,IF(H33<2.5,$L$5,IF(H33<3.5,$L$4,IF(H33<4.5,$L$3,"n/a")))) -> Not at all
A34: =Questionnaire!$A$101 -> 6. LIVING CONDITIONS
A35: =Questionnaire!$A$102 -> 6.1 Health services | B35: =Questionnaire!J106 -> 2.6666667 | C35: =IF(B35<1.5,$L$6,IF(B35<2.5,$L$5,IF(B35<3.5,$L$4,IF(B35<4.5,$L$3,"n/a")))) -> Substantial | D35: =IF(H35<B35,"↑",IF(H35>B35,"↓","↔")) -> ↑ | H35: 0 | I35: =IF(H35<1.5,$L$6,IF(H35<2.5,$L$5,IF(H35<3.5,$L$4,IF(H35<4.5,$L$3,"n/a")))) -> Not at all
A36: =Questionnaire!$A$107 -> 6.2 Housing | B36: =Questionnaire!J110 -> 2.5 | C36: =IF(B36<1.5,$L$6,IF(B36<2.5,$L$5,IF(B36<3.5,$L$4,IF(B36<4.5,$L$3,"n/a")))) -> Substantial | D36: =IF(H36<B36,"↑",IF(H36>B36,"↓","↔")) -> ↑ | H36: 0 | I36: =IF(H36<1.5,$L$6,IF(H36<2.5,$L$5,IF(H36<3.5,$L$4,IF(H36<4.5,$L$3,"n/a")))) -> Not at all
A37: =Questionnaire!$A$111 -> 6.3 Education and training | B37: =Questionnaire!J115 -> 3 | C37: =IF(B37<1.5,$L$6,IF(B37<2.5,$L$5,IF(B37<3.5,$L$4,IF(B37<4.5,$L$3,"n/a")))) -> Substantial | D37: =IF(H37<B37,"↑",IF(H37>B37,"↓","↔")) -> ↑ | H37: 0 | I37: =IF(H37<1.5,$L$6,IF(H37<2.5,$L$5,IF(H37<3.5,$L$4,IF(H37<4.5,$L$3,"n/a")))) -> Not at all
A38: =Questionnaire!$A$116 -> 6.4 Mobility ?????? | B38: =Questionnaire!J120 -> n/a | C38: =IF(B38<1.5,$L$6,IF(B38<2.5,$L$5,IF(B38<3.5,$L$4,IF(B38<4.5,$L$3,"n/a")))) -> n/a | D38: =IF(H38<B38,"↑",IF(H38>B38,"↓","↔")) -> ↑ | H38: 0 | I38: =IF(H38<1.5,$L$6,IF(H38<2.5,$L$5,IF(H38<3.5,$L$4,IF(H38<4.5,$L$3,"n/a")))) -> Not at all
A39: Average | B39: =IF(COUNT(B35:B38)=0,"n/a",(AVERAGE(B35:B38))) -> 2.7222222 | C39: =IF(B39<1.5,$L$6,IF(B39<2.5,$L$5,IF(B39<3.5,$L$4,IF(B39<4.5,$L$3,"n/a")))) -> Substantial | D39: =IF(H39<B39,"↑",IF(H39>B39,"↓","↔")) -> ↑ | H39: =AVERAGE(H35:H38) -> 0 | I39: =IF(H39<1.5,$L$6,IF(H39<2.5,$L$5,IF(H39<3.5,$L$4,IF(H39<4.5,$L$3,"n/a")))) -> Not at all

Sheet Questionnaire
A1: Value chain: | B1: =Profile!F1 -> Maize | C1: Country: | D1: =Profile!E2 -> Georgia | F1: Date Last Modification: | J1: =Profile!B3 -> . . / . . / 20 . . | L1: Explanations
A2: Question | C2: Source | D2: Score level | E2: Count | F2: Comments
A3: 1. WORKING CONDITIONS | N3: High | O3: 4.5
A4: 1.1 Respect of labour rights | N4: Substantial | O4: 3.5
A5: 1.1.1 To what extent do companies involved in the value chain respect the standards elaborated in the 8 fundamental ILO international labour conventions and in the ICESCR and ICCPR? | C5: Interviews with farmers, workers. And reports. | D5: Moderate/Low | E5: =IF(D5=$N$6,1,IF(D5=$N$5,2,IF(D5=$N$4,3,IF(D5=$N$3,4,"n/a")))) -> 2 | F5: Respect for labor rights is generally relatively low in Georgia,workers are informaly emploeed in most cases and the treatment of the workers is shaped by sultural traditions and farmers will. | N5: Moderate/Low | O5: 2.5
A6: 1.1.2 Is freedom of association allowed and effective (collective bargaining)? | C6: Interviews with large farms, workers | D6: Moderate/Low | E6: =IF(D6=$N$6,1,IF(D6=$N$5,2,IF(D6=$N$4,3,IF(D6=$N$3,4,"n/a")))) -> 2 | F6: While freedom of association is legally protected, the structure and operational modalities of workers' unions are heavily influenced by their Soviet-era heritage. Consequently, the connection between workers in agricultural enterprises and trade unions is almost absent. Collective bargaining cases are limited within the maiz value chain. | N6: Not at all | O6: 1.5
A7: 1.1.3 To what extent do workers benefit from enforceable and fair contracts | C7: Interviews with large farms, workers | D7: Moderate/Low | E7: =IF(D7=$N$6,1,IF(D7=$N$5,2,IF(D7=$N$4,3,IF(D7=$N$3,4,"n/a")))) -> 2 | F7: Written contracts are absent in most cases and the contracts are exiting mostly in alrge farms and only skilled workers have this contracts. However, the farmers give the free work days and their work is often based on informal (verbal) agreements. The same applies to the sesonal workers. | N7: n/a
A8: 1.1.4 To what extent are risks of forced labour in any segment of the value chain minimised? | C8: Interviews with large farms, workers | D8: Substantial | E8: =IF(D8=$N$6,1,IF(D8=$N$5,2,IF(D8=$N$4,3,IF(D8=$N$3,4,"n/a")))) -> 3 | F8: During the fieldwork, the research team did not observe any instances of forced labor within the wheat value chain.
A9: 1.1.5 To what extent are any risks of discrimination in employment for specific categories of the population minimised? | C9: Interviews with large farms, workers | D9: Substantial | E9: =IF(D9=$N$6,1,IF(D9=$N$5,2,IF(D9=$N$4,3,IF(D9=$N$3,4,"n/a")))) -> 3 | F9: No instances of discrimination were reported by any interviewees.
C10: Average: | D10: =IF(E10<1.5,$N$6,IF(E10<2.5,$N$5,IF(E10<3.5,$N$4,IF(E10<4.5,$N$3,"n/a")))) -> Moderate/Low | E10: =IF(COUNT(E5:E9)=0,"n/a",AVERAGE(E5:E9)) -> 2.4 | F10: =E10 -> 2.4 | H10: Final: | I10: =D10 -> Moderate/Low | J10: =IF(I10=$N$7,"n/a",IF(AND(I10=$N$5,D10=$N$6),1.5,IF(AND(I10=$N$4,D10=$N$5),2.5,IF(AND(I10=$N$3,D10=$N$4),3.5,IF(AND(I10=$N$6,D10=$N$5),1.49,IF(AND(I10=$N$5,D10=$N$4),2.49,IF(AND(I10=$N$4,D10=$N$3),3.49,E10))))))) -> 2.4 | K10: Justification if adjustment of the score level = …
A11: 1.2 Child Labour
A12: 1.2.1 Degree of school attendance in case children are working (in any segment of the value chain)? | C12: Interviews farmers, workers, statistics | D12: High | E12: =IF(D12=$N$6,1,IF(D12=$N$5,2,IF(D12=$N$4,3,IF(D12=$N$3,4,"n/a")))) -> 4 | F12: School attendance is extremely high for both rural and urban children. | L12: Cf: Guidance
A13: 1.2.2 Are children protected from exposure to harmful jobs? | C13: interviews farmers, workers, statistics | D13: High | E13: =IF(D13=$N$6,1,IF(D13=$N$5,2,IF(D13=$N$4,3,IF(D13=$N$3,4,"n/a")))) -> 4 | F13: Factory work is prohibited for children under 18, and we saw no evidence of it. . | L13: Cf: Guidance
C14: Average: | D14: =IF(E14<1.5,$N$6,IF(E14<2.5,$N$5,IF(E14<3.5,$N$4,IF(E14<4.5,$N$3,"n/a")))) -> High | E14: =IF(COUNT(E12:E13)=0,"n/a",AVERAGE(E12:E13)) -> 4 | F14: =E14 -> 4 | H14: Final: | I14: =D14 -> High | J14: =IF(I14=$N$7,"n/a",IF(AND(I14=$N$5,D14=$N$6),1.5,IF(AND(I14=$N$4,D14=$N$5),2.5,IF(AND(I14=$N$3,D14=$N$4),3.5,IF(AND(I14=$N$6,D14=$N$5),1.49,IF(AND(I14=$N$5,D14=$N$4),2.49,IF(AND(I14=$N$4,D14=$N$3),3.49,E14))))))) -> 4 | K14: Justification if adjustment of the score level = …
A15: 1.3 Job safety
A16: 1.3.1 Degree of protection from accidents and health damages (in any segment of the value chain)? | C16: interviews farmers, workers, statistics | D16: Moderate/Low | E16: =IF(D16=$N$6,1,IF(D16=$N$5,2,IF(D16=$N$4,3,IF(D16=$N$3,4,"n/a")))) -> 2 | F16: The large have some safity standards altough the useage of protection measures and facilities while working with pesticades and herbicades is relatively low. The presence of working inspecction ate the farm gate is absent.
C17: Average: | D17: =IF(E17<1.5,$N$6,IF(E17<2.5,$N$5,IF(E17<3.5,$N$4,IF(E17<4.5,$N$3,"n/a")))) -> Moderate/Low | E17: =IF(COUNT(E16)=0,"n/a",AVERAGE(E16)) -> 2 | F17: =E17 -> 2 | H17: Final: | I17: =D17 -> Moderate/Low | J17: =IF(I17=$N$7,"n/a",IF(AND(I17=$N$5,D17=$N$6),1.5,IF(AND(I17=$N$4,D17=$N$5),2.5,IF(AND(I17=$N$3,D17=$N$4),3.5,IF(AND(I17=$N$6,D17=$N$5),1.49,IF(AND(I17=$N$5,D17=$N$4),2.49,IF(AND(I17=$N$4,D17=$N$3),3.49,E17))))))) -> 2 | K17: Justification if adjustment of the score level = …
A18: 1.4 Attractiveness
A19: 1.4.1 To what extent are remunerations in accordance with local standards? | C19: interviews farmers, workers, statistics | D19: Substantial | E19: =IF(D19=$N$6,1,IF(D19=$N$5,2,IF(D19=$N$4,3,IF(D19=$N$3,4,"n/a")))) -> 3 | F19: The avarige salaries of the workers are a lower then the avarige salary in Georgia. Altouhg, adminsitration adn mechanisators have relatively high salary. | L19: Cf: Guidance
A20: 1.4.2 Are conditions of activities attractive for youth? | C20: interviews farmers, workers, statistics | D20: Moderate/Low | E20: =IF(D20=$N$6,1,IF(D20=$N$5,2,IF(D20=$N$4,3,IF(D20=$N$3,4,"n/a")))) -> 2 | F20: The workers in farms are in most cases above 50 years old. In rare cases the youth are interesting to become farmer and have their land then to work in agricultrual enterprises
C21: Average: | D21: =IF(E21<1.5,$N$6,IF(E21<2.5,$N$5,IF(E21<3.5,$N$4,IF(E21<4.5,$N$3,"n/a")))) -> Substantial | E21: =IF(COUNT(E19:E20)=0,"n/a",AVERAGE(E19:E20)) -> 2.5 | F21: =E21 -> 2.5 | H21: Final: | I21: =D21 -> Substantial | J21: =IF(I21=$N$7,"n/a",IF(AND(I21=$N$5,D21=$N$6),1.5,IF(AND(I21=$N$4,D21=$N$5),2.5,IF(AND(I21=$N$3,D21=$N$4),3.5,IF(AND(I21=$N$6,D21=$N$5),1.49,IF(AND(I21=$N$5,D21=$N$4),2.49,IF(AND(I21=$N$4,D21=$N$3),3.49,E21))))))) -> 2.5 | K21: Justification if adjustment of the score level = …
A22: 2. LAND & WATER RIGHTS
A23: 2.1 Adherence to VGGT | L23: Cf: Guidance
A24: 2.1.1 Do the companies/institutions involved in the value chain declare adhering to the VGGT? | C24: Interviews, academic literature | D24: Moderate/Low | E24: =IF(D24=$N$6,1,IF(D24=$N$5,2,IF(D24=$N$4,3,IF(D24=$N$3,4,"n/a")))) -> 2 | F24: The fars are facing with water scaricty and drainage problems. The VGGT standards are less known to the farmers. | L24: Cf: Guidance
A25: 2.1.2 If large scale investments for land aquisition are at stake, do the involved companies/institutions apply the 'Guide to due diligence of agribusiness projects that affect land and property rights'? | C25: Interviews, academic literature | D25: Substantial | E25: =IF(D25=$N$6,1,IF(D25=$N$5,2,IF(D25=$N$4,3,IF(D25=$N$3,4,"n/a")))) -> 3 | F25: it is regulated by the law of agricultural land.
C26: Average: | D26: =IF(E26<1.5,"Low",IF(E26<2.5,"Moderate",IF(E26<3.5,"Substantial",IF(E26<4.5,"High","n/a")))) -> Substantial | E26: =IF(COUNT(E24:E25)=0,"n/a",AVERAGE(E24:E25)) -> 2.5 | F26: =E26 -> 2.5 | H26: Final: | I26: =D26 -> Substantial | J26: =IF(I26=$N$7,"n/a",IF(AND(I26=$N$5,D26=$N$6),1.5,IF(AND(I26=$N$4,D26=$N$5),2.5,IF(AND(I26=$N$3,D26=$N$4),3.5,IF(AND(I26=$N$6,D26=$N$5),1.49,IF(AND(I26=$N$5,D26=$N$4),2.49,IF(AND(I26=$N$4,D26=$N$3),3.49,E26))))))) -> 2.5 | K26: Justification if adjustment of the score level = …
A27: 2.2 Transparency, participation and consultation
A28: 2.2.1 Level of prior disclosure of project related information to local stakeholders? | C28: Interviews, academic literature | D28: Moderate/Low | E28: =IF(D28=$N$6,1,IF(D28=$N$5,2,IF(D28=$N$4,3,IF(D28=$N$3,4,"n/a")))) -> 2 | F28: Agricuotural enterprises are well aware of the project implemented by the government a
A29: 2.2.2 Level of accessibility of intervention policies, laws, procedures and decisions to all stakeholders of the value chain? | C29: Interviews with herders and soum level officials | D29: Substantial | E29: =IF(D29=$N$6,1,IF(D29=$N$5,2,IF(D29=$N$4,3,IF(D29=$N$3,4,"n/a")))) -> 3 | F29: Agricultural enterprises have relatively high awernes of the govermental policy issues. To certain extent they have influence on it. Whareas the small farmers awerness and influence remains low.
A30: 2.2.3 Level of participation and consultation of all individuals and groups in the decision-making process? | C30: Interviews with herders and soum level officials | D30: Moderate/Low | E30: =IF(D30=$N$6,1,IF(D30=$N$5,2,IF(D30=$N$4,3,IF(D30=$N$3,4,"n/a")))) -> 2 | F30: The agricultural enterprises representatives have certain laverigies to provide advocacy campaing or other forms of infleunce including protest ralies to influnece goverment decision making.
A31: 2.2.4 To what extent prior consent of those affected by the decisions was reached? | D31: n/a | E31: =IF(D31=$N$6,1,IF(D31=$N$5,2,IF(D31=$N$4,3,IF(D31=$N$3,4,"n/a")))) -> n/a | L31: Cf: Guidance
C32: Average: | D32: =IF(E32<1.5,"Low",IF(E32<2.5,"Moderate",IF(E32<3.5,"Substantial",IF(E32<4.5,"High","n/a")))) -> Moderate | E32: =IF(COUNT(E28:E31)=0,"n/a",AVERAGE(E28:E31)) -> 2.3333333 | F32: =E32 -> 2.3333333 | H32: Final: | I32: =D32 -> Moderate | J32: =IF(I32=$N$7,"n/a",IF(AND(I32=$N$5,D32=$N$6),1.5,IF(AND(I32=$N$4,D32=$N$5),2.5,IF(AND(I32=$N$3,D32=$N$4),3.5,IF(AND(I32=$N$6,D32=$N$5),1.49,IF(AND(I32=$N$5,D32=$N$4),2.49,IF(AND(I32=$N$4,D32=$N$3),3.49,E32))))))) -> 2.3333333 | K32: Justification if adjustment of the score level = …
A33: 2.3 Equity,compensation and justice
A34: 2.3.1 Do the locally applied rules promote secure and equitable tenure rights or access to land and water? | C34: Interviews with herders and soum-level officials | D34: Substantial | E34: =IF(D34=$N$6,1,IF(D34=$N$5,2,IF(D34=$N$4,3,IF(D34=$N$3,4,"n/a")))) -> 3 | F34: The law related of the land use is outdated the government works to elaborate and approve new law related to the land use. Altough, local applied rules related to the heritage renting of the land are informaly and formaly regulated. No signitifact issues were reported during the field visits. | L34: Cf: Guidance
A35: 2.3.2 In case disruption of livelihoods is expected, have alternative strategies been considered? | D35: Substantial | E35: =IF(D35=$N$6,1,IF(D35=$N$5,2,IF(D35=$N$4,3,IF(D35=$N$3,4,"n/a")))) -> 3 | F35: When the farmers are reporting the loses the government provides subsisades altouhg the workers in agricultural enterpriuses are sometimes without salaries due to loses of the farmers.
A36: 2.3.3 Where expropriation is indispensable: is a system for ensuring fair and prompt compensation in place (in accordance with the national law and publically acknowledged as being fair)? | D36: n/a | E36: =IF(D36=$N$6,1,IF(D36=$N$5,2,IF(D36=$N$4,3,IF(D36=$N$3,4,"n/a")))) -> n/a | F36: There were no expropriation cases reported during the field mission.
A37: 2.3.4 Are there provisions foreseen to address stakeholder complains and for arbitration of possible conflicts caused by value chain investments? | C37: Interviews with herders and soum-level officials | D37: Substantial | E37: =IF(D37=$N$6,1,IF(D37=$N$5,2,IF(D37=$N$4,3,IF(D37=$N$3,4,"n/a")))) -> 3 | F37: There are several assotiations working and advociatieng the issues bothered the farmers.
C38: Average: | D38: =IF(E38<1.5,"Low",IF(E38<2.5,"Moderate",IF(E38<3.5,"Substantial",IF(E38<4.5,"High","n/a")))) -> Substantial | E38: =IF(COUNT(E34:E37)=0,"n/a",AVERAGE(E34:E37)) -> 3 | F38: =E38 -> 3 | H38: Final: | I38: =D38 -> Substantial | J38: =IF(I38=$N$7,"n/a",IF(AND(I38=$N$5,D38=$N$6),1.5,IF(AND(I38=$N$4,D38=$N$5),2.5,IF(AND(I38=$N$3,D38=$N$4),3.5,IF(AND(I38=$N$6,D38=$N$5),1.49,IF(AND(I38=$N$5,D38=$N$4),2.49,IF(AND(I38=$N$4,D38=$N$3),3.49,E38))))))) -> 3 | K38: Justification if adjustment of the score level = …
A39: 3. GENDER EQUALITY
A40: 3.1 Economic activities
A41: 3.1.1 Are risks of women being excluded from certain segments of the value chain minimised? | C41: Interviews, observation | D41: Substantial | E41: =IF(D41=$N$6,1,IF(D41=$N$5,2,IF(D41=$N$4,3,IF(D41=$N$3,4,"n/a")))) -> 3 | F41: Women participate moslty in the administration and catering servicies of the agricultural etnerprises including mediaum farms. | L41: Cf: Guidance
A42: 3.1.2 To what extent are women active in the value chain (as producers, processors, workers, traders…)? | C42: Interviews, observation | D42: Substantial | E42: =IF(D42=$N$6,1,IF(D42=$N$5,2,IF(D42=$N$4,3,IF(D42=$N$3,4,"n/a")))) -> 3 | F42: As 3.1.1
C43: Average: | D43: =IF(E43<1.5,"Low",IF(E43<2.5,"Moderate",IF(E43<3.5,"Substantial",IF(E43<4.5,"High","n/a")))) -> Substantial | E43: =IF(COUNT(E41:E42)=0,"n/a",AVERAGE(E41:E42)) -> 3 | F43: =E43 -> 3 | H43: Final: | I43: =D43 -> Substantial | J43: =IF(I43=$N$7,"n/a",IF(AND(I43=$N$5,D43=$N$6),1.5,IF(AND(I43=$N$4,D43=$N$5),2.5,IF(AND(I43=$N$3,D43=$N$4),3.5,IF(AND(I43=$N$6,D43=$N$5),1.49,IF(AND(I43=$N$5,D43=$N$4),2.49,IF(AND(I43=$N$4,D43=$N$3),3.49,E43))))))) -> 3 | K43: Justification if adjustment of the score level = …
A44: 3.2 Access to resources and services
A45: 3.2.1 Do women have ownership of assets (other than land)? | C45: Interviews with herders, reports | D45: Moderate/Low | E45: =IF(D45=$N$6,1,IF(D45=$N$5,2,IF(D45=$N$4,3,IF(D45=$N$3,4,"n/a")))) -> 2 | F45: The agroicultural land ownership is gendered, most part of owners are man heritaged the agricultural land.
A46: 3.2.2 Do women have equal land rights as men? | C46: Interviews with herders, reports | D46: Substantial | E46: =IF(D46=$N$6,1,IF(D46=$N$5,2,IF(D46=$N$4,3,IF(D46=$N$3,4,"n/a")))) -> 3 | F46: As 3.2.2.
A47: 3.2.3 Do women have access to credit? | C47: Interviews with herders, reports | D47: Moderate/Low | E47: =IF(D47=$N$6,1,IF(D47=$N$5,2,IF(D47=$N$4,3,IF(D47=$N$3,4,"n/a")))) -> 2 | F47: Women have acsses to the credit but in value chain mostly man are dominated.
A48: 3.2.4 Do women have access to other services (extension services, inputs…)? | C48: Interviews with herders, reports | D48: Substantial | E48: =IF(D48=$N$6,1,IF(D48=$N$5,2,IF(D48=$N$4,3,IF(D48=$N$3,4,"n/a")))) -> 3 | F48: Access to extension services is limited for both genders, altouhg women farmers are participating in the proejcts implemented by NGOs to sopport women trough differtt capacity building programmes and grant funding.
C49: Average: | D49: =IF(E49<1.5,"Low",IF(E49<2.5,"Moderate",IF(E49<3.5,"Substantial",IF(E49<4.5,"High","n/a")))) -> Substantial | E49: =IF(COUNT(E45:E48)=0,"n/a",AVERAGE(E45:E48)) -> 2.5 | F49: =E49 -> 2.5 | H49: Final: | I49: =D49 -> Substantial | J49: =IF(I49=$N$7,"n/a",IF(AND(I49=$N$5,D49=$N$6),1.5,IF(AND(I49=$N$4,D49=$N$5),2.5,IF(AND(I49=$N$3,D49=$N$4),3.5,IF(AND(I49=$N$6,D49=$N$5),1.49,IF(AND(I49=$N$5,D49=$N$4),2.49,IF(AND(I49=$N$4,D49=$N$3),3.49,E49))))))) -> 2.5 | K49: Justification if adjustment of the score level = …
A50: 3.3 Decision making
A51: 3.3.1 To what extent do women take part in the decisions related to production? | C51: Interviews with herders, reports | D51: Moderate/Low | E51: =IF(D51=$N$6,1,IF(D51=$N$5,2,IF(D51=$N$4,3,IF(D51=$N$3,4,"n/a")))) -> 2 | F51: Women are invloved in the decision making is low. Excluding rare women managing the farm.
A52: 3.3.2 To what extent are women autonomous in the organisation of their work? | C52: Interviews with herders, reports | D52: Substantial | E52: =IF(D52=$N$6,1,IF(D52=$N$5,2,IF(D52=$N$4,3,IF(D52=$N$3,4,"n/a")))) -> 3 | F52: Women in most agricultral enterprises lack the invlovment in decision making.
A53: 3.3.3 Do women have control over income? | C53: Interviews with herders, reports | D53: Substantial | E53: =IF(D53=$N$6,1,IF(D53=$N$5,2,IF(D53=$N$4,3,IF(D53=$N$3,4,"n/a")))) -> 3 | F53: Women have less say omn the distrubution of income on agricultural enterprises in small farms their invovment is relatively high.
A54: 3.3.4 Do women earn independent income? | C54: Interviews with herders, reports, national statistics | D54: High | E54: =IF(D54=$N$6,1,IF(D54=$N$5,2,IF(D54=$N$4,3,IF(D54=$N$3,4,"n/a")))) -> 4 | F54: Nationally, women have indipendetn income
A55: 3.2.5 Do women take part in decisions on the purchase, sale or transfer of assets? | C55: Interviews with herders, reports | D55: Moderate/Low | E55: =IF(D55=$N$6,1,IF(D55=$N$5,2,IF(D55=$N$4,3,IF(D55=$N$3,4,"n/a")))) -> 2 | F55: Their invovment in this process is low.
C56: Average: | D56: =IF(E56<1.5,"Low",IF(E56<2.5,"Moderate",IF(E56<3.5,"Substantial",IF(E56<4.5,"High","n/a")))) -> Substantial | E56: =IF(COUNT(E51:E55)=0,"n/a",AVERAGE(E51:E55)) -> 2.8 | F56: =E56 -> 2.8 | H56: Final: | I56: =D56 -> Substantial | J56: =IF(I56=$N$7,"n/a",IF(AND(I56=$N$5,D56=$N$6),1.5,IF(AND(I56=$N$4,D56=$N$5),2.5,IF(AND(I56=$N$3,D56=$N$4),3.5,IF(AND(I56=$N$6,D56=$N$5),1.49,IF(AND(I56=$N$5,D56=$N$4),2.49,IF(AND(I56=$N$4,D56=$N$3),3.49,E56))))))) -> 2.8 | K56: Justification if adjustment of the score level = …
A57: 3.4 Leadership and empowerment
A58: 3.4.1 Are women members of groups, trade unions, farmers' organisations? | C58: Interviews | D58: Substantial | E58: =IF(D58=$N$6,1,IF(D58=$N$5,2,IF(D58=$N$4,3,IF(D58=$N$3,4,"n/a")))) -> 3 | F58: In assotiations related to the cerials women invovment are relatively low altouhg in some farmers assotiations women are managers and their role is high
A59: 3.4.2 Do women have leadership positions within the organisations they are part of? | C59: Interviews | D59: Substantial | E59: =IF(D59=$N$6,1,IF(D59=$N$5,2,IF(D59=$N$4,3,IF(D59=$N$3,4,"n/a")))) -> 3 | F59: Same as 3.4.1
A60: 3.4.3 Do women have the power to influence services, territorial power and policy decision making? | C60: Interviews | D60: Moderate/Low | E60: =IF(D60=$N$6,1,IF(D60=$N$5,2,IF(D60=$N$4,3,IF(D60=$N$3,4,"n/a")))) -> 2 | F60: Yes, but less so than men
A61: 3.4.4 Do women speak in public? | C61: Interviews, reports | D61: High | E61: =IF(D61=$N$6,1,IF(D61=$N$5,2,IF(D61=$N$4,3,IF(D61=$N$3,4,"n/a")))) -> 4 | F61: Yes, no issues were reported or observed.
C62: Average: | D62: =IF(E62<1.5,"Low",IF(E62<2.5,"Moderate",IF(E62<3.5,"Substantial",IF(E62<4.5,"High","n/a")))) -> Substantial | E62: =IF(COUNT(E58:E61)=0,"n/a",AVERAGE(E58:E61)) -> 3 | F62: =E62 -> 3 | H62: Final: | I62: =D62 -> Substantial | J62: =IF(I62=$N$7,"n/a",IF(AND(I62=$N$5,D62=$N$6),1.5,IF(AND(I62=$N$4,D62=$N$5),2.5,IF(AND(I62=$N$3,D62=$N$4),3.5,IF(AND(I62=$N$6,D62=$N$5),1.49,IF(AND(I62=$N$5,D62=$N$4),2.49,IF(AND(I62=$N$4,D62=$N$3),3.49,E62))))))) -> 3 | K62: Justification if adjustment of the score level = …
A63: 3.5 Hardship and division of labour
A64: 3.5.1 To what extent are the overall work loads of men and women equal (including domestic work and child care)? | C64: Interviews, reports | D64: Substantial | E64: =IF(D64=$N$6,1,IF(D64=$N$5,2,IF(D64=$N$4,3,IF(D64=$N$3,4,"n/a")))) -> 3 | F64: In wheath productions mechanisation and heavy work is done mostly by Men. In small farmes women are invoved more in domestic work and child care.
A65: 3.5.2 Are risks of women being subject to strenuous work minimised (e.g. using labour saving technologies…)? | C65: Interviews, reports, observation | D65: Substantial | E65: =IF(D65=$N$6,1,IF(D65=$N$5,2,IF(D65=$N$4,3,IF(D65=$N$3,4,"n/a")))) -> 3 | F65: Man are working more strenuous in wheth production but women work is also hard in some cases.
C66: Average: | D66: =IF(E66<1.5,"Low",IF(E66<2.5,"Moderate",IF(E66<3.5,"Substantial",IF(E66<4.5,"High","n/a")))) -> Substantial | E66: =IF(COUNT(E64:E65)=0,"n/a",AVERAGE(E64:E65)) -> 3 | F66: =E66 -> 3 | H66: Final: | I66: =D66 -> Substantial | J66: =IF(I66=$N$7,"n/a",IF(AND(I66=$N$5,D66=$N$6),1.5,IF(AND(I66=$N$4,D66=$N$5),2.5,IF(AND(I66=$N$3,D66=$N$4),3.5,IF(AND(I66=$N$6,D66=$N$5),1.49,IF(AND(I66=$N$5,D66=$N$4),2.49,IF(AND(I66=$N$4,D66=$N$3),3.49,E66))))))) -> 3 | K66: Justification if adjustment of the score level = …
A67: 4. FOOD AND NUTRITION SECURITY | L67: Cf: Guidance
A68: 4.1 Availability of food
A69: 4.1.1 Does the local production of food increase? | C69: National statistics, interviews | D69: Substantial | E69: =IF(D69=$N$6,1,IF(D69=$N$5,2,IF(D69=$N$4,3,IF(D69=$N$3,4,"n/a")))) -> 3 | F69: Severe food insecurity is very rare, altouhg Russion invasion in Ukraine coused to the government of Moldova to start discussion on food security strategy ,eaboration. | L69: Cf: Guidance
A70: 4.1.2 Are food supplies increasing on local markets? | C70: National statistics, interviews | D70: Substantial | E70: =IF(D70=$N$6,1,IF(D70=$N$5,2,IF(D70=$N$4,3,IF(D70=$N$3,4,"n/a")))) -> 3 | F70: There are many food supplaiers in local market. | L70: Cf: Guidance
C71: Average: | D71: =IF(E71<1.5,"Low",IF(E71<2.5,"Moderate",IF(E71<3.5,"Substantial",IF(E71<4.5,"High","n/a")))) -> Substantial | E71: =IF(COUNT(E69:E70)=0,"n/a",AVERAGE(E69:E70)) -> 3 | F71: =E71 -> 3 | H71: Final: | I71: =D71 -> Substantial | J71: =IF(I71=$N$7,"n/a",IF(AND(I71=$N$5,D71=$N$6),1.5,IF(AND(I71=$N$4,D71=$N$5),2.5,IF(AND(I71=$N$3,D71=$N$4),3.5,IF(AND(I71=$N$6,D71=$N$5),1.49,IF(AND(I71=$N$5,D71=$N$4),2.49,IF(AND(I71=$N$4,D71=$N$3),3.49,E71))))))) -> 3 | K71: Justification if adjustment of the score level = …
A72: 4.2 Accessibility of food
A73: 4.2.1 Do people have more income to allocate to food? | C73: National statistics, interviews, observations | D73: Substantial | E73: =IF(D73=$N$6,1,IF(D73=$N$5,2,IF(D73=$N$4,3,IF(D73=$N$3,4,"n/a")))) -> 3 | F73: Owners and workers of all type of whath farms are able to allocate income for food.
A74: 4.2.2 Are (relative) consumers food prices decreasing? | C74: National statistics, interviews | D74: Moderate/Low | E74: =IF(D74=$N$6,1,IF(D74=$N$5,2,IF(D74=$N$4,3,IF(D74=$N$3,4,"n/a")))) -> 2 | F74: Food price inflation is at manageable levels. In 2024 was around 5%. | L74: Cf: Guidance
C75: Average: | D75: =IF(E75<1.5,"Low",IF(E75<2.5,"Moderate",IF(E75<3.5,"Substantial",IF(E75<4.5,"High","n/a")))) -> Substantial | E75: =IF(COUNT(E73:E74)=0,"n/a",AVERAGE(E73:E74)) -> 2.5 | F75: =E75 -> 2.5 | H75: Final: | I75: =D75 -> Substantial | J75: =IF(I75=$N$7,"n/a",IF(AND(I75=$N$5,D75=$N$6),1.5,IF(AND(I75=$N$4,D75=$N$5),2.5,IF(AND(I75=$N$3,D75=$N$4),3.5,IF(AND(I75=$N$6,D75=$N$5),1.49,IF(AND(I75=$N$5,D75=$N$4),2.49,IF(AND(I75=$N$4,D75=$N$3),3.49,E75))))))) -> 2.5 | K75: Justification if adjustment of the score level = …
A76: 4.3 Utilisation and nutritional adequacy
A77: 4.3.1 Is the nutritional quality of available food improving? | C77: National statistics, interviews | D77: Substantial | E77: =IF(D77=$N$6,1,IF(D77=$N$5,2,IF(D77=$N$4,3,IF(D77=$N$3,4,"n/a")))) -> 3 | F77: There are relatively low concerns on nutritional food quality in Moldova.
A78: 4.3.2 Are nutritional practices being improved? | C78: National statistics, interviews | D78: Substantial | E78: =IF(D78=$N$6,1,IF(D78=$N$5,2,IF(D78=$N$4,3,IF(D78=$N$3,4,"n/a")))) -> 3 | F78: According to the acegdotal evidancies nutritional practicies are being imporved. | L78: Cf: Guidance
A79: 4.3.3 Is dietary diversity increased? | C79: National statistics, interviews | D79: Substantial | E79: =IF(D79=$N$6,1,IF(D79=$N$5,2,IF(D79=$N$4,3,IF(D79=$N$3,4,"n/a")))) -> 3 | F79: Same as 4.3.2. | L79: Cf: Guidance
C80: Average: | D80: =IF(E80<1.5,"Low",IF(E80<2.5,"Moderate",IF(E80<3.5,"Substantial",IF(E80<4.5,"High","n/a")))) -> Substantial | E80: =IF(COUNT(E77:E79)=0,"n/a",AVERAGE(E77:E79)) -> 3 | F80: =E80 -> 3 | H80: Final: | I80: =D80 -> Substantial | J80: =IF(I80=$N$7,"n/a",IF(AND(I80=$N$5,D80=$N$6),1.5,IF(AND(I80=$N$4,D80=$N$5),2.5,IF(AND(I80=$N$3,D80=$N$4),3.5,IF(AND(I80=$N$6,D80=$N$5),1.49,IF(AND(I80=$N$5,D80=$N$4),2.49,IF(AND(I80=$N$4,D80=$N$3),3.49,E80))))))) -> 3 | K80: Justification if adjustment of the score level = …
A81: 4.4 Stability
A82: 4.4.1 Is risk of periodic food shortage for household reduced? | D82: Substantial | E82: =IF(D82=$N$6,1,IF(D82=$N$5,2,IF(D82=$N$4,3,IF(D82=$N$3,4,"n/a")))) -> 3 | F82: There are no reports or observation of the food shortage reported
A83: 4.4.2 Is excessive food price variation reduced? | D83: Moderate/Low | E83: =IF(D83=$N$6,1,IF(D83=$N$5,2,IF(D83=$N$4,3,IF(D83=$N$3,4,"n/a")))) -> 2 | F83: Please add justification. | L83: Cf: Guidance
C84: Average: | D84: =IF(E84<1.5,"Low",IF(E84<2.5,"Moderate",IF(E84<3.5,"Substantial",IF(E84<4.5,"High","n/a")))) -> Substantial | E84: =IF(COUNT(E82:E83)=0,"n/a",AVERAGE(E82:E83)) -> 2.5 | F84: =E84 -> 2.5 | H84: Final: | I84: =D84 -> Substantial | J84: =IF(I84=$N$7,"n/a",IF(AND(I84=$N$5,D84=$N$6),1.5,IF(AND(I84=$N$4,D84=$N$5),2.5,IF(AND(I84=$N$3,D84=$N$4),3.5,IF(AND(I84=$N$6,D84=$N$5),1.49,IF(AND(I84=$N$5,D84=$N$4),2.49,IF(AND(I84=$N$4,D84=$N$3),3.49,E84))))))) -> 2.5 | K84: Justification if adjustment of the score level = …
A85: 5. SOCIAL CAPITAL
A86: 5.1 Strength of producer organisations
A87: 5.1.1 Do formal and informal farmer organisations /cooperatives participate in the value chain? | C87: Interviews | D87: Substantial | E87: =IF(D87=$N$6,1,IF(D87=$N$5,2,IF(D87=$N$4,3,IF(D87=$N$3,4,"n/a")))) -> 3 | F87: The farmers organisation participate in the valua chain especialy to advocate farmers issues related to the government and export.
A88: 5.1.2 How inclusive is group/cooperative membership? | C88: Interviews | D88: Moderate/Low | E88: =IF(D88=$N$6,1,IF(D88=$N$5,2,IF(D88=$N$4,3,IF(D88=$N$3,4,"n/a")))) -> 2 | F88: Cooperatives influence and participation is low. | L88: Cf: Guidance
A89: 5.1.3 Do groups have representative and accountable leadership? | C89: Interviews | D89: Moderate/Low | E89: =IF(D89=$N$6,1,IF(D89=$N$5,2,IF(D89=$N$4,3,IF(D89=$N$3,4,"n/a")))) -> 2 | F89: The agricultural enterprises have representatives in the asostiations.
A90: 5.1.4 Are farmer groups, cooperatives and associations able to negotiate in input or output markets? | C90: Interviews, economic analysis | D90: Substantial | E90: =IF(D90=$N$6,1,IF(D90=$N$5,2,IF(D90=$N$4,3,IF(D90=$N$3,4,"n/a")))) -> 3 | F90: The groups especialy agricultural enterprises nagotiate in input and output markets.
C91: Average: | D91: =IF(E91<1.5,"Low",IF(E91<2.5,"Moderate",IF(E91<3.5,"Substantial",IF(E91<4.5,"High","n/a")))) -> Substantial | E91: =IF(COUNT(E87:E90)=0,"n/a",AVERAGE(E87:E90)) -> 2.5 | F91: =E91 -> 2.5 | H91: Final: | I91: =D91 -> Substantial | J91: =IF(I91=$N$7,"n/a",IF(AND(I91=$N$5,D91=$N$6),1.5,IF(AND(I91=$N$4,D91=$N$5),2.5,IF(AND(I91=$N$3,D91=$N$4),3.5,IF(AND(I91=$N$6,D91=$N$5),1.49,IF(AND(I91=$N$5,D91=$N$4),2.49,IF(AND(I91=$N$4,D91=$N$3),3.49,E91))))))) -> 2.5 | K91: Justification if adjustment of the score level = …
A92: 5.2 Information and confidence
A93: 5.2.1 Do farmers in the value chain have access to information on agricultural practices, agricultural policies, and market prices? | C93: Interviews | D93: Substantial | E93: =IF(D93=$N$6,1,IF(D93=$N$5,2,IF(D93=$N$4,3,IF(D93=$N$3,4,"n/a")))) -> 3 | F93: Farmers use multiply of informations this applies especialy to the agricultral enterprises and medium farms.
A94: 5.2.2 To what extent is the relation between value chain actors perceived as trustworthy? | C94: Interviews | D94: Substantial | E94: =IF(D94=$N$6,1,IF(D94=$N$5,2,IF(D94=$N$4,3,IF(D94=$N$3,4,"n/a")))) -> 3 | F94: Horisontal trust between value chain actors is relatively high, Vertical trust towards govermental insitutions is relatively low. | L94: Cf: Guidance
C95: Average: | D95: =IF(E95<1.5,"Low",IF(E95<2.5,"Moderate",IF(E95<3.5,"Substantial",IF(E95<4.5,"High","n/a")))) -> Substantial | E95: =IF(COUNT(E93:E94)=0,"n/a",AVERAGE(E93:E94)) -> 3 | F95: =E95 -> 3 | H95: Final: | I95: =D95 -> Substantial | J95: =IF(I95=$N$7,"n/a",IF(AND(I95=$N$5,D95=$N$6),1.5,IF(AND(I95=$N$4,D95=$N$5),2.5,IF(AND(I95=$N$3,D95=$N$4),3.5,IF(AND(I95=$N$6,D95=$N$5),1.49,IF(AND(I95=$N$5,D95=$N$4),2.49,IF(AND(I95=$N$4,D95=$N$3),3.49,E95))))))) -> 3 | K95: Justification if adjustment of the score level = …
A96: 5.3 Social involvement
A97: 5.3.1 Do communities participate in decisions that impact their livelihood? | C97: Interviews | D97: Substantial | E97: =IF(D97=$N$6,1,IF(D97=$N$5,2,IF(D97=$N$4,3,IF(D97=$N$3,4,"n/a")))) -> 3 | F97: Medium farmers and agrocultural enterprises are invoved in the community related decisions. | L97: Cf: Guidance
A98: 5.3.2 Are there actions to ensure respect of traditional knowledge and resources? | C98: Interviews | D98: Substantial | E98: =IF(D98=$N$6,1,IF(D98=$N$5,2,IF(D98=$N$4,3,IF(D98=$N$3,4,"n/a")))) -> 3 | F98: Agricultural enterprises partialy use the practiscies established during the Sovit Union. | L98: Cf: Guidance
A99: 5.3.3 Is there participation in voluntary communal activities for benefit of the community | C99: Interviews, reports | D99: High | E99: =IF(D99=$N$6,1,IF(D99=$N$5,2,IF(D99=$N$4,3,IF(D99=$N$3,4,"n/a")))) -> 4 | F99: Strong voluntary participation in neighbourhood activities such as well maintenance, forest establishement, road maintenance, etc.
C100: Average: | D100: =IF(E100<1.5,"Low",IF(E100<2.5,"Moderate",IF(E100<3.5,"Substantial",IF(E100<4.5,"High","n/a")))) -> Substantial | E100: =IF(COUNT(E97:E99)=0,"n/a",AVERAGE(E97:E99)) -> 3.3333333 | F100: =E100 -> 3.3333333 | H100: Final: | I100: =D100 -> Substantial | J100: =IF(I100=$N$7,"n/a",IF(AND(I100=$N$5,D100=$N$6),1.5,IF(AND(I100=$N$4,D100=$N$5),2.5,IF(AND(I100=$N$3,D100=$N$4),3.5,IF(AND(I100=$N$6,D100=$N$5),1.49,IF(AND(I100=$N$5,D100=$N$4),2.49,IF(AND(I100=$N$4,D100=$N$3),3.49,E100))))))) -> 3.3333333 | K100: Justification if adjustment of the score level = …
...

Sheet Guidance
A1: How to use the Social Profile Tool
A2: When using this Excel tool, please take into account the following guiding principles:
A3: * | B3: Only fill in blank cells and select score levels as they appear in the drop-down lists of the questionnaire! Grey cells are automatically filled based on previous entries. Grey cells should never be changed by the user.
A4: ** | B4: Be careful in using "copy and paste" function that covers more than one cell, as you might interfere with non-visible formulas or cells used for calculations.
A5: *** | B5: When writing comments and observation with text ending beyond the limits of the cell, you can adjust the row height by dragging down the bottom line of the row from the far left colum which shows the row numbers.
A6: It is recommended to follow the steps below:
A7: Profile sheet
A8: 1 | B8: Fill in the name of the value chain, country and the date of assessment in the first sheet "Profile". They will be copied automatically in the other sheets from where you cannot access these elements.
A9: Questionnaire sheet
A10: =+A8+1 -> 2 | B10: Respond to each question by using the score levels: - High, - Substantial, - Moderate/Low, - Not at all, - n/a = not applicable (when not relevant) or not available (when not possible to reply). In your assessment, take into account the likelihood and the impact and consider the stage of the chain the most at risk.
A11: =+A10+1 -> 3 | B11: Give a short justification for your choice in the "Comments" column.
A12: =+A11+1 -> 4 | B12: In the column "Source", you should include which source of information you used for your judgement.
A13: =+A12+1 -> 5 | B13: The "Average" score level is automatically set as the unweighted average of the score levels for the underlying questions. In exceptional cases, the average score level can be manually modified using column I (cell next to "Final:"). This may be used in order to take into account important aspects not covered by the questions. In this case, a justification should be provided (under "Comments", column K). Change can only be done to the immediate nearest score level or to n/a (otherwise the calculations will be wrong). NB: After making trials of adjustment of this cell, if you eventually want to let the initial automatic calculation work, it is necessary to reintroduce manually the reference of the corresponding D cell ("=Dx" for line x) to come back to the intial state of the spreadsheet.
A14: Register sheet
A15: =+A13+1 -> 6 | B15: Describe the major risks, if any, in column E. All the questions assessed as "not at all" or "moderate/low" in the questionnaire need to be analyzed as possible risks or negative outcomes. Major risks and negative consequences may be identified by the questionnaire, but could also include further issues to be pointed at.
A16: =+A15+1 -> 7 | B16: Describe the major mitigating measures in column F.
A17: =+A16+1 -> 8 | B17: Insert date and copy scores of previous social profile assessment (column H), if there has been one.
A18: =+A17+1 -> 9 | B18: Highlight progress done in the implementation of specific measures since previous social profile assessment in column G "Comments".
A19: Profile sheet
A20: =+A18+1 -> 10 | B20: Provide an overall summary of the key issues and recommendations, the Risk and Cost of Non-Intervention vs. Benefits and the key mitigating measures.
A21: Warning | B21: After some time of work and changes, it happens that colours are not automatically selected. => Save your work, close the file and open it again… and it will work afresh!
A24: Question n° | B24: Explanations on questions
A25: 1.2.1 | B25: Risk assessment
A26: 1.2.2 | B26: Risk assessment
A27: 1.4.1 | B27: Remuneration: provision of income allowing workers to support themselves and their families.
A28: 2.1 | B28: Consider as entry point for the analysis the current state of play of the country specific land governance (policy, legislation, institutions/actors, enacting and application of legislation in particular as regards the consideration/impact on smallholders, land administration). This is important to know/judge if government legislation and/or customary rights matter
A29: 2.1.1 | B29: How is adherence to VGGT done and is this publically acknowledged?
A30: 2.2.4 | B30: Respond 'High' if formal contract exists
A31: 2.3.1 | B31: Practice of legal recognition and allocation of land rights in the sphere of value chain investment: formal, customary and informal land rights, rights of indigenous people, pastoralists, contracts… To which extent doeas the value chain investment impact on local/traditional land governance?
A32: 3.1.1 | B32: Good reasons for restictions make the question non applicable
A33: 4 | B33: The complexity of the food and nutrition security sector implies that, for the purpose of this social profile, it should be analysed from the point of view of changes and evolution of the systems
A34: 4.1.1 | B34: Does food availability increase? Production,export Yc transports (trucks…).
A35: 4.1.2 | B35: Import, transport, stock, market institutions.
A36: 4.2.2 | B36: Impact on food prices; impact on revenues => link with Economic analysis.
A37: 4.3.2 | B37: As nutritional practices please consider: nutrition policies and strategies, nutrition-training, education, the setting up of coordination mechanisms between agriculture, health, education, and social protection sectors. Do such nutritional practises target pregnant and lactating women as well as children under five (with a stronger emphasis on those under the age of two)?
A38: 4.3.3 | B38: Minimum number of food groups consumed by an individual over a reference period. Ref.: FAO Manual Minimum Dietary Diversity in Women (in preparation). This is relevant only if the baseline score is low.
A39: 4.4.2 | B39: Price variation can be seasonal or transitory due to any type of shock.
A40: 5.1.2 | B40: Inclusiveness viewed from different perspectives: wealth strata, age, gender, ethnic or social groups…
A41: 5.2.2 | B41: Verbal agreement, long lasting collaboration, contract, market, hierarchy… Looking upstream and downstream the VC.
A42: 5.3.1 | B42: CFS RAI: principle 9 on meanigful information, consultation and decision making processes.
A43: 5.3.2 | B43: CFS RAI: principle 7 on respect cultural heritage and traditional knowledge and support diversity and innovation.
A44: 6.1.1 | B44: Health facilities: health center, buildings, equipments…
A45: 6.1.2 | B45: Health services: availabilty of nurse, doctors…
... A47: 6.3.3 | B47: The reply to this question might be 'non applicable' if the reply to 5.3.2 is 'high'.
E49: Initial count | F49: Ranges used for averages
B50: How does the profile calculate? è è è è è è è è | D50: Used in sheets: | E50: "Questionnaire" | F50: "Questionnaire", "Register" and "Profile"
D51: High | E51: 4 | F51: ≥ 3.5
D52: Substantial | E52: 3 | F52: 2.50 ≤ < 3.50
D53: Moderate/Low | E53: 2 | F53: 1.50 ≤ < 2.50
D54: Not at all | E54: 1 | F54: < 1.50
D55: n/a | E55: - | F55: -
